{
  "brand" : "Roco",
  "itemNumber" : "62576",
  "scale" : "H0",
  "category" : "LOCOMOTIVES",
  "description" : "Set due E645 castano/isabella senza modanature, gocciolatoio, 066 motorizzata tetto e fregio castano portelloni bassi + 035 folle tetto isabella fregio rosso portelloni alti, dep. MI Sm.",
  "details" : null,
  "powerMethod" : "DC",
  "deliveryDate" : "2009",
  "availabilityStatus" : "AVAILABLE",
  "rollingStocks" : [ {
    "category" : "LOCOMOTIVE",
    "className" : "E645",
    "roadNumber" : "E645 066 + E645 035",
    "series" : "SECONDA SERIE",
    "locomotiveType" : "ELECTRIC_LOCOMOTIVE",
    "railway" : "FS",
    "epoch" : "IVb",
    "depot" : "",
    "dccInterface" : "NONE",
    "control" : "DCC_READY",
    "livery" : "",
    "lengthOverBuffer" : {
      "inches" : null,
      "millimeters" : null
    },
    "technicalSpecifications" : {
      "minimumRadius" : 360.0,
      "coupling" : {
        "socket" : null,
        "closeCouplers" : "NO",
        "digitalShunting" : "NO"
      },
      "flywheelFitted" : "NO",
      "metalBody" : "NO",
      "interiorLights" : "NO",
      "lights" : "YES",
      "springBuffers" : "NO"
    },
    "dummy" : false
  } ],
  "count" : 1
}