{
  "brand" : "Roco",
  "itemNumber" : "72891",
  "scale" : "H0",
  "category" : "LOCOMOTIVES",
  "description" : "Serie 1000 OM, vetri curvi, modanature in rilievo, griglia curva, 2 scarichi centrali, dep. Torino",
  "details" : null,
  "powerMethod" : "DC",
  "deliveryDate" : "",
  "availabilityStatus" : "AVAILABLE",
  "rollingStocks" : [ {
    "category" : "LOCOMOTIVE",
    "className" : "D343",
    "roadNumber" : "D343 1014",
    "series" : "",
    "locomotiveType" : "DIESEL_LOCOMOTIVE",
    "railway" : "FS",
    "epoch" : "IVa",
    "depot" : "",
    "dccInterface" : "NONE",
    "control" : "DCC_READY",
    "livery" : "",
    "lengthOverBuffer" : {
      "inches" : null,
      "millimeters" : null
    },
    "technicalSpecifications" : {
      "minimumRadius" : 360.0,
      "coupling" : {
        "socket" : null,
        "closeCouplers" : "NO",
        "digitalShunting" : "NO"
      },
      "flywheelFitted" : "NO",
      "metalBody" : "NO",
      "interiorLights" : "NO",
      "lights" : "YES",
      "springBuffers" : "NO"
    },
    "dummy" : false
  } ],
  "count" : 1
}