{
  "brand": "Rivarossi/Hornby",
  "item_number": "HR2904S",
  "scale": "H0",
  "category": "LOCOMOTIVES",
  "power_method": "DC",
  "epoch": "VI",
  "description": {
    "de": null,
    "en": null,
    "fr": null,
    "it": "FS, locomotiva elettrica E.402B, nuova livrea “Frecciabianca”, ep. VI"
  },
  "details": {
    "de": null,
    "en": null,
    "fr": null,
    "it": ""
  },
  "delivery_date": "2023/09",
  "availability_status": "AVAILABLE",
  "rolling_stocks": [
    {
      "category": "LOCOMOTIVE",
      "railway": "FS",
      "livery": "Frecciabianca",
      "length_over_buffers": {
        "inches": 8.7795323,
        "millimeters": 223.0
      },
      "technical_specifications": {
        "minimum_radius": 360.0,
        "coupling": {
          "socket": "NEM_362",
          "close_couplers": "YES",
          "digital_shunting": "NO"
        },
        "flywheel_fitted": null,
        "metal_body": null,
        "interior_lights": "NO",
        "lights": "YES",
        "spring_buffers": null
      },
      "class_name": "E.402B",
      "road_number": "E.402B 164",
      "series": null,
      "depot": null,
      "locomotive_type": "ELECTRIC_LOCOMOTIVE",
      "dcc_interface": "MTC_21",
      "control": "DCC_SOUND",
      "is_dummy": false
    }
  ],
  "count": 1
}