{
  "brand" : "ESU",
  "itemNumber" : "31291",
  "scale" : "H0",
  "category" : "LOCOMOTIVES",
  "description" : "Gr. 897 “Pierina” nero telaio rosso, marcatura a biacca",
  "details" : null,
  "powerMethod" : "DC",
  "deliveryDate" : "",
  "availabilityStatus" : "AVAILABLE",
  "rollingStocks" : [ {
    "category" : "LOCOMOTIVE",
    "className" : "897",
    "roadNumber" : "897 001",
    "series" : "(ex BR 94 DB / T16.1 KPEV)",
    "locomotiveType" : "STEAM_LOCOMOTIVE",
    "railway" : "FS",
    "epoch" : "II",
    "depot" : "",
    "dccInterface" : "NONE",
    "control" : "DCC_READY",
    "livery" : "",
    "lengthOverBuffer" : {
      "inches" : null,
      "millimeters" : null
    },
    "technicalSpecifications" : {
      "minimumRadius" : 360.0,
      "coupling" : {
        "socket" : null,
        "closeCouplers" : "NO",
        "digitalShunting" : "NO"
      },
      "flywheelFitted" : "NO",
      "metalBody" : "NO",
      "interiorLights" : "NO",
      "lights" : "YES",
      "springBuffers" : "NO"
    },
    "dummy" : false
  } ],
  "count" : 1
}